stbridge.cpython-311-darwin.so
stbridge-0.1.1.dist-info/RECORD
stbridge-0.1.1.dist-info/LICENSE
stbridge-0.1.1.dist-info/WHEEL
stbridge-0.1.1.dist-info/top_level.txt
stbridge-0.1.1.dist-info/METADATA
