Metadata-Version: 2.1
Name: stbridge
Version: 0.1.1
Summary: Python wrapper for STLINK-V3-BRIDGE
Author-email: Matthew Tran <matthewlamtran@berkeley.edu>
Project-URL: Homepage, https://github.com/dragonlock2/stbridge
Project-URL: Issues, https://github.com/dragonlock2/stbridge/issues
Classifier: Programming Language :: Python :: 3
Classifier: Operating System :: OS Independent
Requires-Python: >=3.9
License-File: LICENSE
